nautobot_api_sandbox/__init__.py
nautobot_api_sandbox/click_ui.py
nautobot_api_sandbox/nauto_demo_functions.py
nautobot_api_sandbox/nautobot_api_sandbox_ui.py
nautobot_api_sandbox-0.1.6.dist-info/METADATA
nautobot_api_sandbox-0.1.6.dist-info/WHEEL
nautobot_api_sandbox-0.1.6.dist-info/entry_points.txt
nautobot_api_sandbox-0.1.6.dist-info/RECORD
