Metadata-Version: 2.1
Name: nautobot-api-sandbox
Version: 0.1.6
Summary: This is just a simple program to test my programing knowledge and to learn more about API and Nautobot.
Author: tPayne0647
Requires-Python: >=3.9,<4.0
Classifier: Programming Language :: Python :: 3
Classifier: Programming Language :: Python :: 3.9
Classifier: Programming Language :: Python :: 3.10
Classifier: Programming Language :: Python :: 3.11
Requires-Dist: pynautobot (==1.5.0)
